Beetroot/__init__.py
Beetroot/engine.py
Beetroot/fundamental.py
Beetroot/parallel.py
Beetroot/plotting.py
Beetroot/py.typed
Beetroot/signal.py
Beetroot/utils.py
Beetroot/LZS/LZS_Signal.py
Beetroot/LZS/LZS_parallel.py
Beetroot/LZS/__init__.py
Beetroot/LZS/py.typed
Beetroot_SEB-1.1.0.dist-info/LICENSE
Beetroot_SEB-1.1.0.dist-info/METADATA
Beetroot_SEB-1.1.0.dist-info/WHEEL
Beetroot_SEB-1.1.0.dist-info/top_level.txt
Beetroot_SEB-1.1.0.dist-info/RECORD
