Metadata-Version: 2.1
Name: Beetroot-SEB
Version: 1.1.0
Summary: Beetroot - The definitive library for Single Elctron Box simulations
Author-email: Lorenzo Peri <lorenzo@quantummotion.tech>
License: GNU GENERAL PUBLIC LICENSE
Project-URL: Homepage, https://https://github.com/LorenzoPeri17/Beetroot
Requires-Python: >=3.9
License-File: LICENSE
Requires-Dist: numpy
Requires-Dist: scipy
Requires-Dist: matplotlib
Requires-Dist: numba
Requires-Dist: numba-scipy
Requires-Dist: mpmath
Provides-Extra: test
Requires-Dist: pytest ; extra == 'test'
